jb_drf_auth/__init__.py
jb_drf_auth/apps.py
jb_drf_auth/backends.py
jb_drf_auth/checks.py
jb_drf_auth/conf.py
jb_drf_auth/email_templates.py
jb_drf_auth/managers.py
jb_drf_auth/permissions.py
jb_drf_auth/urls.py
jb_drf_auth/utils.py
jb_drf_auth/models/__init__.py
jb_drf_auth/models/base.py
jb_drf_auth/providers/__init__.py
jb_drf_auth/providers/aws_sns.py
jb_drf_auth/providers/base.py
jb_drf_auth/providers/django_email.py
jb_drf_auth/serializers/__init__.py
jb_drf_auth/serializers/device.py
jb_drf_auth/serializers/email_confirmation.py
jb_drf_auth/serializers/login.py
jb_drf_auth/serializers/otp.py
jb_drf_auth/serializers/password_reset.py
jb_drf_auth/serializers/profile.py
jb_drf_auth/serializers/register.py
jb_drf_auth/serializers/user.py
jb_drf_auth/serializers/user_admin.py
jb_drf_auth/services/__init__.py
jb_drf_auth/services/client.py
jb_drf_auth/services/email_confirmation.py
jb_drf_auth/services/login.py
jb_drf_auth/services/me.py
jb_drf_auth/services/otp.py
jb_drf_auth/services/password_reset.py
jb_drf_auth/services/register.py
jb_drf_auth/services/tokens.py
jb_drf_auth/views/__init__.py
jb_drf_auth/views/account_management.py
jb_drf_auth/views/email_confirmation.py
jb_drf_auth/views/login.py
jb_drf_auth/views/me.py
jb_drf_auth/views/otp.py
jb_drf_auth/views/password_reset.py
jb_drf_auth/views/profile.py
jb_drf_auth/views/register.py
jb_drf_auth/views/user_admin.py
jb_drf_auth-0.1.0.dist-info/licenses/LICENSE
jb_drf_auth-0.1.0.dist-info/METADATA
jb_drf_auth-0.1.0.dist-info/WHEEL
jb_drf_auth-0.1.0.dist-info/top_level.txt
jb_drf_auth-0.1.0.dist-info/RECORD
