Metadata-Version: 2.4
Name: jb-drf-auth
Version: 0.1.0
Summary: Reusable auth + profiles foundations for Django/DRF projects
Requires-Python: >=3.11
License-File: LICENSE
Requires-Dist: Django>=5.0
Requires-Dist: djangorestframework>=3.15
Requires-Dist: djangorestframework-simplejwt>=5.3
Requires-Dist: drf-extra-fields>=3.7
Requires-Dist: django-filter>=24.2
Requires-Dist: django-safedelete<2.0,>=1.4
Requires-Dist: argon2-cffi~=25.1.0
Requires-Dist: bcrypt~=4.0.1
Requires-Dist: boto3>=1.34
Requires-Dist: Pillow>=10.0
Dynamic: license-file
